lookup_property/__init__.py
lookup_property/converters/__init__.py
lookup_property/converters/aggregates.py
lookup_property/converters/cast.py
lookup_property/converters/conditions.py
lookup_property/converters/datetime.py
lookup_property/converters/expressions.py
lookup_property/converters/functions.py
lookup_property/converters/lookups.py
lookup_property/converters/main.py
lookup_property/converters/math.py
lookup_property/converters/number.py
lookup_property/converters/string.py
lookup_property/converters/utils.py
lookup_property/decorator.py
lookup_property/dispatch.py
lookup_property/expressions.py
lookup_property/field.py
lookup_property/py.typed
lookup_property/typing.py
django_lookup_property-0.2.2.dist-info/LICENSE
django_lookup_property-0.2.2.dist-info/METADATA
django_lookup_property-0.2.2.dist-info/WHEEL
django_lookup_property-0.2.2.dist-info/RECORD
