Metadata-Version: 2.3
Name: django-lookup-property
Version: 0.2.2
Summary: Django model properties that are also lookup expressions.
License: MIT
Keywords: django,lookup,property,orm,model,extension
Author: Matti Lamppu
Author-email: lamppu.matti.akseli@gmail.com
Requires-Python: >=3.11,<4
Classifier: Environment :: Web Environment
Classifier: Operating System :: OS Independent
Classifier: Intended Audience :: Developers
Classifier: Natural Language :: English
Classifier: Programming Language :: Python
Classifier: Programming Language :: Python :: 3
Classifier: Programming Language :: Python :: 3 :: Only
Classifier: Programming Language :: Python :: 3.11
Classifier: Programming Language :: Python :: 3.12
Classifier: Programming Language :: Python :: 3.13
Classifier: Framework :: Django :: 5.0
Classifier: Framework :: Django :: 5.1
Classifier: Framework :: Django :: 5.2
Requires-Dist: Django (>=5.0)
Project-URL: Bug Tracker, https://github.com/MrThearMan/django-lookup-property/issues
Project-URL: Documentation, https://mrthearman.github.io/django-lookup-property
Project-URL: Homepage, https://mrthearman.github.io/django-lookup-property
Project-URL: Repository, https://github.com/MrThearMan/django-lookup-property
